govuk_forms/__init__.py
govuk_forms/apps.py
govuk_forms/fields.py
govuk_forms/forms.py
govuk_forms/setup_extensions.py
govuk_forms/widgets.py
govuk_forms/locale/cy/LC_MESSAGES/django.mo
govuk_forms/locale/cy/LC_MESSAGES/django.po
govuk_forms/locale/en_GB/LC_MESSAGES/django.mo
govuk_forms/locale/en_GB/LC_MESSAGES/django.po
govuk_forms/static-src/stylesheets/_govuk-forms.scss
govuk_forms/static-src/stylesheets/elements/forms/_form-date-extensions.scss
govuk_forms/static-src/stylesheets/elements/forms/_form-validation-extensions.scss
govuk_forms/templates/govuk_forms/error-summary.html
govuk_forms/templates/govuk_forms/field-fieldset.html
govuk_forms/templates/govuk_forms/field-no-label.html
govuk_forms/templates/govuk_forms/field.html
govuk_forms/templates/govuk_forms/fieldset.html
govuk_forms/templates/govuk_forms/submit-button.html
govuk_forms/templates/govuk_forms/widgets/checkbox.html
govuk_forms/templates/govuk_forms/widgets/multiple-select-option.html
govuk_forms/templates/govuk_forms/widgets/multiple-select.html
govuk_forms/templates/govuk_forms/widgets/split-date.html
django_govuk_forms-0.7.dist-info/LICENSE.txt
django_govuk_forms-0.7.dist-info/METADATA
django_govuk_forms-0.7.dist-info/WHEEL
django_govuk_forms-0.7.dist-info/top_level.txt
django_govuk_forms-0.7.dist-info/RECORD
