Metadata-Version: 2.1
Name: django-govuk-forms
Version: 0.7
Summary: Django app that creates forms based on Government Digital Services style guide
Home-page: https://github.com/ministryofjustice/django-govuk-forms
Author: Ministry of Justice
Author-email: dev@digital.justice.gov.uk
License: MIT
Keywords: django govuk template forms elements frontend toolkit
Platform: UNKNOWN
Classifier: Development Status :: 4 - Beta
Classifier: Framework :: Django
Classifier: Intended Audience :: Developers
Classifier: License :: OSI Approved :: MIT License
Classifier: Natural Language :: English
Classifier: Operating System :: OS Independent
Classifier: Programming Language :: Python :: 3
Classifier: Programming Language :: Python :: 3.5
Classifier: Programming Language :: Python :: 3.6
Classifier: Programming Language :: Python :: 3.7
Requires-Dist: django (>=1.11)
